MANIFEST.in
README.rst
setup.py
docs/HISTORY.txt
docs/LICENSE.GPL
docs/LICENSE.txt
ftw/__init__.py
ftw.subsite.egg-info/PKG-INFO
ftw.subsite.egg-info/SOURCES.txt
ftw.subsite.egg-info/dependency_links.txt
ftw.subsite.egg-info/entry_points.txt
ftw.subsite.egg-info/namespace_packages.txt
ftw.subsite.egg-info/not-zip-safe
ftw.subsite.egg-info/requires.txt
ftw.subsite.egg-info/top_level.txt
ftw/subsite/__init__.py
ftw/subsite/config.py
ftw/subsite/configure.zcml
ftw/subsite/interfaces.py
ftw/subsite/languages.py
ftw/subsite/lawgiver.zcml
ftw/subsite/negotiator.py
ftw/subsite/overrides.zcml
ftw/subsite/permissions.zcml
ftw/subsite/profilehooks.py
ftw/subsite/resources.zcml
ftw/subsite/testing.py
ftw/subsite/traverse.py
ftw/subsite/utils.py
ftw/subsite/vocabularies.py
ftw/subsite/Extensions/install.py
ftw/subsite/browser/__init__.py
ftw/subsite/browser/configure.zcml
ftw/subsite/browser/contact.py
ftw/subsite/browser/languageselector.pt
ftw/subsite/browser/manage-subsiteview.pt
ftw/subsite/browser/mobile_button.py
ftw/subsite/browser/selector.py
ftw/subsite/browser/sitemap.py
ftw/subsite/browser/subsiteview.pt
ftw/subsite/browser/subsiteview.py
ftw/subsite/browser/resources/dropdown.js
ftw/subsite/browser/resources/integration.ftw-mobile.theme.scss
ftw/subsite/browser/resources/integration.theme.scss
ftw/subsite/browser/resources/main.css
ftw/subsite/browser/resources/main.js
ftw/subsite/browser/resources/subsite-compiled.css
ftw/subsite/browser/resources/subsite-compiled.js
ftw/subsite/browser/resources/subsite.css
ftw/subsite/content/__init__.py
ftw/subsite/content/configure.zcml
ftw/subsite/content/subsite.py
ftw/subsite/content/subsitedx.py
ftw/subsite/locales/ftw.lawgiver.pot
ftw/subsite/locales/ftw.subsite-manual.pot
ftw/subsite/locales/ftw.subsite.pot
ftw/subsite/locales/plone.pot
ftw/subsite/locales/de/LC_MESSAGES/ftw.lawgiver.po
ftw/subsite/locales/de/LC_MESSAGES/ftw.subsite.po
ftw/subsite/locales/de/LC_MESSAGES/plone.po
ftw/subsite/migration/__init__.py
ftw/subsite/migration/subsite_migration.py
ftw/subsite/portlets/__init__.py
ftw/subsite/portlets/configure.zcml
ftw/subsite/portlets/widget/__init__.py
ftw/subsite/portlets/widget/image.py
ftw/subsite/profiles/default/actions.xml
ftw/subsite/profiles/default/browserlayer.xml
