Metadata-Version: 2.1
Name: ftw.subsite
Version: 2.7.8
Summary: UNKNOWN
Home-page: https://github.com/4teamwork/ftw.subsite
Author: 4teamwork AG
Author-email: mailto:info@4teamwork.ch
License: GPL2
Keywords: ftw subsite
Platform: UNKNOWN
Classifier: Framework :: Plone
Classifier: Framework :: Plone :: 4.3
Classifier: Framework :: Plone :: 5.1
Classifier: Programming Language :: Python
Classifier: Topic :: Software Development :: Libraries :: Python Modules
Provides-Extra: tests
Provides-Extra: test
Provides-Extra: plone4
